<!-- edited with XMLSPY v5 rel. 2 U (http://www.xmlspy.com) by Warroom (Big Huge Games) -->
<!-- LOCALIZATION: LEADER and CITY elements; also, name attribute -->
<TRIBE name="西班牙人" substitute="1">
  <LEADERS>
    <LEADER>查理四世</LEADER>
  </LEADERS>
  <CITIES>
    <CITY>马德里</CITY>
    <CITY>托雷多</CITY>
    <CITY>塞维尔</CITY>
    <CITY>哥多华</CITY>
    <CITY>卡迪兹</CITY>
    <CITY>卡斯提亚</CITY>
    <CITY>萨拉戈萨</CITY>
    <CITY>巴塞隆纳</CITY>
    <CITY>瓦伦西亚</CITY>
    <CITY>马拉加</CITY>
    <CITY>塞拉曼加</CITY>
    <CITY>瓦拉朵丽</CITY>
    <CITY>博格斯</CITY>
    <CITY>雷昂</CITY>
    <CITY>雷阿尔城</CITY>
    <CITY>维哥</CITY>
    <CITY>科鲁尼亚</CITY>
    <CITY>奥维多</CITY>
    <CITY>毕尔包</CITY>
    <CITY>潘普洛纳</CITY>
    <CITY>莫西亚</CITY>
    <CITY>格兰那达</CITY>
    <CITY>桑坦德</CITY>
    <CITY>阿兰蕙斯</CITY>
    <CITY>阿曼沙</CITY>
    <CITY>阿利甘地</CITY>
    <CITY>欧苏纳</CITY>
    <CITY>阿吉西拉斯</CITY>
    <CITY>亚美利亚</CITY>
    <CITY>塞哥维亚</CITY>
    <CITY>巴达霍斯</CITY>
    <CITY>塔拉韦拉</CITY>
    <CITY>维多利亚</CITY>
    <CITY>赫雷斯</CITY>
    <CITY>希洪</CITY>
  </CITIES>
  <UNIT_CONTINENT>0 European</UNIT_CONTINENT>
  <BUILD_CONTINENT>0 Med</BUILD_CONTINENT>
  <BACKUP_BUILD_CONTINENT>0 Med</BACKUP_BUILD_CONTINENT>
</TRIBE>